{"name":"Automatic Control Basic Course Exercises 2022","previewImagePath":"","source":"https://control.lth.se/fileadmin/control/Education/EngineeringProgram/FRTF05/exercises_print.pdf","chapters":[{"fullname":"Model Building and Linearization","number":1,"tasks":[{"task":1},{"task":2},{"task":3},{"task":4},{"task":5},{"task":6},{"task":7},{"task":8},{"task":9}]},{"fullname":"Dynamical Systems","number":2,"tasks":[{"task":1},{"task":2},{"task":3},{"task":4},{"task":5},{"task":6},{"task":7},{"task":8},{"task":9},{"task":10},{"task":11},{"task":12},{"task":13},{"task":14},{"task":15},{"task":16}]},{"fullname":"Frequency Analysis","number":3,"tasks":[{"task":1},{"task":2},{"task":3},{"task":4},{"task":5},{"task":6},{"task":7}]},{"fullname":"Feedback Systems","number":4,"tasks":[{"task":1},{"task":2},{"task":3},{"task":4},{"task":5},{"task":6},{"task":7},{"task":8},{"task":9},{"task":10},{"task":11},{"task":12},{"task":13},{"task":14},{"task":15},{"task":16},{"task":17},{"task":18},{"task":19}]},{"fullname":"State Feedback and Kalman Filtering","number":5,"tasks":[{"task":1},{"task":2},{"task":3},{"task":4},{"task":5},{"task":6},{"task":7},{"task":8},{"task":9},{"task":10},{"task":11},{"task":12},{"task":13}]},{"fullname":"Design methods","number":6,"tasks":[{"task":1},{"task":2},{"task":3},{"task":4},{"task":5},{"task":6},{"task":7},{"task":8},{"task":9},{"task":10},{"task":11},{"task":12},{"task":13},{"task":14},{"task":15},{"task":16}]},{"fullname":"Controller Structures","number":7,"tasks":[{"task":1},{"task":2},{"task":3},{"task":4},{"task":5},{"task":6},{"task":7},{"task":8},{"task":9},{"task":10}]},{"fullname":"Design Examples","number":8,"tasks":[{"task":1},{"task":2}]},{"fullname":"Interactive Comparison Between Model Descriptions","number":9,"tasks":[{"task":1},{"task":2},{"task":3}]}],"generatorVersion":"1.0.5","custom":false,"id":"Automatic Control Basic Course Exercises 2022"}